chronodeck/__init__.py
chronodeck-0.1.0.dist-info/METADATA
chronodeck-0.1.0.dist-info/WHEEL
chronodeck-0.1.0.dist-info/entry_points.txt
chronodeck-0.1.0.dist-info/top_level.txt
chronodeck-0.1.0.dist-info/RECORD
