Metadata-Version: 2.4
Name: chronodeck
Version: 0.1.0
Summary: Chronodeck
Author: Your Name
Author-email: your.email@example.com
Requires-Python: >=3.7
Dynamic: author
Dynamic: author-email
Dynamic: requires-python
Dynamic: summary
